c2validator/__init__.py
c2validator/validator.py
c2validator-1.0.2.dist-info/METADATA
c2validator-1.0.2.dist-info/WHEEL
c2validator-1.0.2.dist-info/licenses/LICENSE
c2validator-1.0.2.dist-info/RECORD
