Metadata-Version: 2.1
Name: c2validator
Version: 1.0.2
Summary: This package validate and generate CPF and CNPJ for tests
Project-URL: Homepage, https://github.com/devguilhermecosta/c2validator
Project-URL: Bug Tracker, https://github.com/devguilhermecosta/c2validator/issues
Author-email: Guilherme Costa <guilherme.partic@gmail.com>
License-File: LICENSE
Classifier: License :: OSI Approved :: MIT License
Classifier: Operating System :: OS Independent
Classifier: Programming Language :: Python :: 3
Requires-Python: >=3.7
